trax_act_controller/__init__.py
trax_act_controller/act.py
trax_act_controller-0.2.4.dist-info/METADATA
trax_act_controller-0.2.4.dist-info/WHEEL
trax_act_controller-0.2.4.dist-info/RECORD
